SOFASonix/SOFASonix.py
SOFASonix/SOFASonixError.py
SOFASonix/SOFASonixField.py
SOFASonix/SOFATemplate.py
SOFASonix/__init__.py
SOFASonix/ss_db.db
SOFASonix-1.0.7.dist-info/LICENSE
SOFASonix-1.0.7.dist-info/METADATA
SOFASonix-1.0.7.dist-info/WHEEL
SOFASonix-1.0.7.dist-info/top_level.txt
SOFASonix-1.0.7.dist-info/RECORD
